spotichart/__about__.py
spotichart/__init__.py
spotichart/language/__init__.py
spotichart/language/main.py
spotichart/lyrics/__about__.py
spotichart/lyrics/__init__.py
spotichart/lyrics/lyrics_scraper.py
spotichart/lyrics/main.py
spotichart/lyrics/track_features.py
spotichart/spotipy/__about__.py
spotichart/spotipy/__init__.py
spotichart/spotipy/audio_features.py
spotichart/spotipy/main.py
spotichart/spotipy/top_charts.py
spotichart-1.0.0.dist-info/LICENSE
spotichart-1.0.0.dist-info/METADATA
spotichart-1.0.0.dist-info/WHEEL
spotichart-1.0.0.dist-info/top_level.txt
spotichart-1.0.0.dist-info/RECORD
