Metadata-Version: 2.1
Name: spotichart
Version: 1.0.0
Summary: Collector Module for Spotify National Trending Analysis
Home-page: https://github.com/larsi-uv/spotichart
Author: Manolomon
Author-email: contacto@manolomon.com
Maintainer: Manolomon
Maintainer-email: contacto@manolomon.com
License: License :: OSI Approved :: MIT License
Platform: UNKNOWN
Classifier: Development Status :: 5 - Production/Stable
Classifier: License :: OSI Approved :: MIT License
Classifier: Intended Audience :: Developers
Classifier: Programming Language :: Python :: 3.6
Classifier: Programming Language :: Python :: 3.7
Classifier: Programming Language :: Python :: 3.8
Classifier: Topic :: Software Development
Classifier: Topic :: Scientific/Engineering :: Information Analysis
Classifier: Topic :: Multimedia :: Sound/Audio :: Analysis
Requires-Python: >=3.6
Requires-Dist: beautifulsoup4 (==4.8.1)
Requires-Dist: bs4 (==0.0.1)
Requires-Dist: certifi (==2019.9.11)
Requires-Dist: chardet (==3.0.4)
Requires-Dist: guess-language-spirit (==0.5.3)
Requires-Dist: idna (==2.8)
Requires-Dist: numpy (==1.17.3)
Requires-Dist: pandas (==0.25.2)
Requires-Dist: python-dateutil (==2.8.0)
Requires-Dist: pytz (==2019.3)
Requires-Dist: requests (==2.22.0)
Requires-Dist: six (==1.12.0)
Requires-Dist: soupsieve (==1.9.4)
Requires-Dist: tqdm (==4.36.1)
Requires-Dist: urllib3 (==1.25.6)
